{
  "page_width_pt": 595.28,
  "page_height_pt": 841.89,
  "pages": [
    {
      "page_index": 0,
      "boxes": [
        {
          "x": 40.0,
          "y": 40.0,
          "width": 515.0,
          "height": 672.0,
          "background_color": null,
          "border": null,
          "text": null,
          "image": null,
          "children": [
            {
              "x": 64.0,
              "y": 64.0,
              "width": 467.0,
              "height": 91.0,
              "background_color": null,
              "border": null,
              "text": null,
              "image": null,
              "children": [
                {
                  "x": 64.0,
                  "y": 78.0,
                  "width": 64.0,
                  "height": 64.0,
                  "background_color": null,
                  "border": null,
                  "text": null,
                  "image": {
                    "src": "data:image/png;base64,iVBORw0KGgoAAAANSUhEUgAAAAEAAAABCAYAAAAfFcSJAAAADUlEQVR42mNk+M9QDwADhgGAWjR9awAAAABJRU5ErkJggg==",
                    "width": 64.0,
                    "height": 64.0
                  },
                  "children": []
                },
                {
                  "x": 144.0,
                  "y": 64.0,
                  "width": 158.0,
                  "height": 91.0,
                  "background_color": null,
                  "border": null,
                  "text": null,
                  "image": null,
                  "children": [
                    {
                      "x": 144.0,
                      "y": 80.0,
                      "width": 158.0,
                      "height": 34.0,
                      "background_color": null,
                      "border": null,
                      "text": {
                        "lines": [
                          {
                            "text": "Company Name",
                            "x_offset": 0.0,
                            "y_offset": 0.0
                          }
                        ],
                        "font_family": "Helvetica",
                        "font_size": 24.0,
                        "bold": true,
                        "italic": false,
                        "color": [
                          0.0,
                          0.0,
                          0.0,
                          1.0
                        ],
                        "line_height": 33.6,
                        "text_align": "left",
                        "underline": false,
                        "list_marker": null
                      },
                      "image": null,
                      "children": []
                    },
                    {
                      "x": 144.0,
                      "y": 126.0,
                      "width": 133.0,
                      "height": 19.0,
                      "background_color": null,
                      "border": null,
                      "text": {
                        "lines": [
                          {
                            "text": "Building the future",
                            "x_offset": 0.0,
                            "y_offset": 0.0
                          }
                        ],
                        "font_family": "Helvetica",
                        "font_size": 14.0,
                        "bold": false,
                        "italic": false,
                        "color": [
                          0.424,
                          0.447,
                          0.502,
                          1.0
                        ],
                        "line_height": 19.6,
                        "text_align": "left",
                        "underline": false,
                        "list_marker": null
                      },
                      "image": null,
                      "children": []
                    }
                  ]
                }
              ]
            },
            {
              "x": 64.0,
              "y": 193.0,
              "width": 176.0,
              "height": 28.0,
              "background_color": null,
              "border": null,
              "text": {
                "lines": [
                  {
                    "text": "Product Overview",
                    "x_offset": 0.0,
                    "y_offset": 0.0
                  }
                ],
                "font_family": "Helvetica",
                "font_size": 20.0,
                "bold": true,
                "italic": false,
                "color": [
                  0.16862746,
                  0.42352942,
                  0.6901961,
                  1.0
                ],
                "line_height": 28.0,
                "text_align": "left",
                "underline": false,
                "list_marker": null
              },
              "image": null,
              "children": []
            },
            {
              "x": 64.0,
              "y": 229.0,
              "width": 464.0,
              "height": 67.0,
              "background_color": null,
              "border": null,
              "text": {
                "lines": [
                  {
                    "text": "Our flagship product combines cutting-edge technology with",
                    "x_offset": 0.0,
                    "y_offset": 0.0
                  },
                  {
                    "text": "user-friendly design. It handles critical workflows across",
                    "x_offset": 0.0,
                    "y_offset": 22.4
                  },
                  {
                    "text": "multiple industries.",
                    "x_offset": 0.0,
                    "y_offset": 44.8
                  }
                ],
                "font_family": "Helvetica",
                "font_size": 16.0,
                "bold": false,
                "italic": false,
                "color": [
                  0.0,
                  0.0,
                  0.0,
                  1.0
                ],
                "line_height": 22.4,
                "text_align": "left",
                "underline": false,
                "list_marker": null
              },
              "image": null,
              "children": []
            },
            {
              "x": 64.0,
              "y": 324.0,
              "width": 79.0,
              "height": 26.0,
              "background_color": null,
              "border": null,
              "text": {
                "lines": [
                  {
                    "text": "Features",
                    "x_offset": 0.0,
                    "y_offset": 0.0
                  }
                ],
                "font_family": "Helvetica",
                "font_size": 18.0,
                "bold": true,
                "italic": false,
                "color": [
                  0.0,
                  0.0,
                  0.0,
                  1.0
                ],
                "line_height": 25.199999,
                "text_align": "left",
                "underline": false,
                "list_marker": null
              },
              "image": null,
              "children": []
            },
            {
              "x": 64.0,
              "y": 358.0,
              "width": 467.0,
              "height": 107.0,
              "background_color": null,
              "border": null,
              "text": null,
              "image": null,
              "children": [
                {
                  "x": 64.0,
                  "y": 358.0,
                  "width": 136.0,
                  "height": 107.0,
                  "background_color": [
                    0.953,
                    0.957,
                    0.961,
                    1.0
                  ],
                  "border": null,
                  "text": null,
                  "image": null,
                  "children": [
                    {
                      "x": 80.0,
                      "y": 374.0,
                      "width": 35.0,
                      "height": 22.0,
                      "background_color": null,
                      "border": null,
                      "text": {
                        "lines": [
                          {
                            "text": "Fast",
                            "x_offset": 0.0,
                            "y_offset": 0.0
                          }
                        ],
                        "font_family": "Helvetica",
                        "font_size": 16.0,
                        "bold": true,
                        "italic": false,
                        "color": [
                          0.0,
                          0.0,
                          0.0,
                          1.0
                        ],
                        "line_height": 22.4,
                        "text_align": "left",
                        "underline": false,
                        "list_marker": null
                      },
                      "image": null,
                      "children": []
                    },
                    {
                      "x": 80.0,
                      "y": 400.0,
                      "width": 98.0,
                      "height": 39.0,
                      "background_color": null,
                      "border": null,
                      "text": {
                        "lines": [
                          {
                            "text": "Sub-second",
                            "x_offset": 0.0,
                            "y_offset": 0.0
                          },
                          {
                            "text": "response times",
                            "x_offset": 0.0,
                            "y_offset": 19.6
                          }
                        ],
                        "font_family": "Helvetica",
                        "font_size": 14.0,
                        "bold": false,
                        "italic": false,
                        "color": [
                          0.0,
                          0.0,
                          0.0,
                          1.0
                        ],
                        "line_height": 19.6,
                        "text_align": "left",
                        "underline": false,
                        "list_marker": null
                      },
                      "image": null,
                      "children": []
                    }
                  ]
                },
                {
                  "x": 216.0,
                  "y": 358.0,
                  "width": 150.0,
                  "height": 107.0,
                  "background_color": [
                    0.953,
                    0.957,
                    0.961,
                    1.0
                  ],
                  "border": null,
                  "text": null,
                  "image": null,
                  "children": [
                    {
                      "x": 232.0,
                      "y": 374.0,
                      "width": 53.0,
                      "height": 22.0,
                      "background_color": null,
                      "border": null,
                      "text": {
                        "lines": [
                          {
                            "text": "Secure",
                            "x_offset": 0.0,
                            "y_offset": 0.0
                          }
                        ],
                        "font_family": "Helvetica",
                        "font_size": 16.0,
                        "bold": true,
                        "italic": false,
                        "color": [
                          0.0,
                          0.0,
                          0.0,
                          1.0
                        ],
                        "line_height": 22.4,
                        "text_align": "left",
                        "underline": false,
                        "list_marker": null
                      },
                      "image": null,
                      "children": []
                    },
                    {
                      "x": 232.0,
                      "y": 400.0,
                      "width": 112.0,
                      "height": 39.0,
                      "background_color": null,
                      "border": null,
                      "text": {
                        "lines": [
                          {
                            "text": "Enterprise-grade",
                            "x_offset": 0.0,
                            "y_offset": 0.0
                          },
                          {
                            "text": "encryption",
                            "x_offset": 0.0,
                            "y_offset": 19.6
                          }
                        ],
                        "font_family": "Helvetica",
                        "font_size": 14.0,
                        "bold": false,
                        "italic": false,
                        "color": [
                          0.0,
                          0.0,
                          0.0,
                          1.0
                        ],
                        "line_height": 19.6,
                        "text_align": "left",
                        "underline": false,
                        "list_marker": null
                      },
                      "image": null,
                      "children": []
                    }
                  ]
                },
                {
                  "x": 382.0,
                  "y": 358.0,
                  "width": 149.0,
                  "height": 107.0,
                  "background_color": [
                    0.953,
                    0.957,
                    0.961,
                    1.0
                  ],
                  "border": null,
                  "text": null,
                  "image": null,
                  "children": [
                    {
                      "x": 398.0,
                      "y": 374.0,
                      "width": 70.0,
                      "height": 22.0,
                      "background_color": null,
                      "border": null,
                      "text": {
                        "lines": [
                          {
                            "text": "Scalable",
                            "x_offset": 0.0,
                            "y_offset": 0.0
                          }
                        ],
                        "font_family": "Helvetica",
                        "font_size": 16.0,
                        "bold": true,
                        "italic": false,
                        "color": [
                          0.0,
                          0.0,
                          0.0,
                          1.0
                        ],
                        "line_height": 22.4,
                        "text_align": "left",
                        "underline": false,
                        "list_marker": null
                      },
                      "image": null,
                      "children": []
                    },
                    {
                      "x": 398.0,
                      "y": 400.0,
                      "width": 112.0,
                      "height": 39.0,
                      "background_color": null,
                      "border": null,
                      "text": {
                        "lines": [
                          {
                            "text": "Handles millions",
                            "x_offset": 0.0,
                            "y_offset": 0.0
                          },
                          {
                            "text": "of requests",
                            "x_offset": 0.0,
                            "y_offset": 19.6
                          }
                        ],
                        "font_family": "Helvetica",
                        "font_size": 14.0,
                        "bold": false,
                        "italic": false,
                        "color": [
                          0.0,
                          0.0,
                          0.0,
                          1.0
                        ],
                        "line_height": 19.6,
                        "text_align": "left",
                        "underline": false,
                        "list_marker": null
                      },
                      "image": null,
                      "children": []
                    }
                  ]
                }
              ]
            },
            {
              "x": 64.0,
              "y": 493.0,
              "width": 69.0,
              "height": 25.0,
              "background_color": null,
              "border": null,
              "text": {
                "lines": [
                  {
                    "text": "Pricing",
                    "x_offset": 0.0,
                    "y_offset": 0.0
                  }
                ],
                "font_family": "Helvetica",
                "font_size": 18.0,
                "bold": true,
                "italic": false,
                "color": [
                  0.0,
                  0.0,
                  0.0,
                  1.0
                ],
                "line_height": 25.199999,
                "text_align": "left",
                "underline": false,
                "list_marker": null
              },
              "image": null,
              "children": []
            },
            {
              "x": 64.0,
              "y": 526.0,
              "width": 467.0,
              "height": 162.0,
              "background_color": null,
              "border": {
                "width": 1.0,
                "color": [
                  0.0,
                  0.0,
                  0.0,
                  1.0
                ]
              },
              "text": null,
              "image": null,
              "children": [
                {
                  "x": 64.0,
                  "y": 526.0,
                  "width": 467.0,
                  "height": 41.0,
                  "background_color": null,
                  "border": null,
                  "text": null,
                  "image": null,
                  "children": [
                    {
                      "x": 64.0,
                      "y": 526.0,
                      "width": 156.0,
                      "height": 41.0,
                      "background_color": [
                        0.898,
                        0.906,
                        0.922,
                        1.0
                      ],
                      "border": {
                        "width": 1.0,
                        "color": [
                          0.0,
                          0.0,
                          0.0,
                          1.0
                        ]
                      },
                      "text": null,
                      "image": null,
                      "children": [
                        {
                          "x": 73.0,
                          "y": 535.0,
                          "width": 32.0,
                          "height": 23.0,
                          "background_color": null,
                          "border": null,
                          "text": {
                            "lines": [
                              {
                                "text": "Plan",
                                "x_offset": 0.0,
                                "y_offset": 0.0
                              }
                            ],
                            "font_family": "Helvetica",
                            "font_size": 16.0,
                            "bold": false,
                            "italic": false,
                            "color": [
                              0.0,
                              0.0,
                              0.0,
                              1.0
                            ],
                            "line_height": 22.4,
                            "text_align": "left",
                            "underline": false,
                            "list_marker": null
                          },
                          "image": null,
                          "children": []
                        }
                      ]
                    },
                    {
                      "x": 220.0,
                      "y": 526.0,
                      "width": 156.0,
                      "height": 41.0,
                      "background_color": [
                        0.898,
                        0.906,
                        0.922,
                        1.0
                      ],
                      "border": {
                        "width": 1.0,
                        "color": [
                          0.0,
                          0.0,
                          0.0,
                          1.0
                        ]
                      },
                      "text": null,
                      "image": null,
                      "children": [
                        {
                          "x": 229.0,
                          "y": 535.0,
                          "width": 40.0,
                          "height": 23.0,
                          "background_color": null,
                          "border": null,
                          "text": {
                            "lines": [
                              {
                                "text": "Users",
                                "x_offset": 0.0,
                                "y_offset": 0.0
                              }
                            ],
                            "font_family": "Helvetica",
                            "font_size": 16.0,
                            "bold": false,
                            "italic": false,
                            "color": [
                              0.0,
                              0.0,
                              0.0,
                              1.0
                            ],
                            "line_height": 22.4,
                            "text_align": "left",
                            "underline": false,
                            "list_marker": null
                          },
                          "image": null,
                          "children": []
                        }
                      ]
                    },
                    {
                      "x": 376.0,
                      "y": 526.0,
                      "width": 155.0,
                      "height": 41.0,
                      "background_color": [
                        0.898,
                        0.906,
                        0.922,
                        1.0
                      ],
                      "border": {
                        "width": 1.0,
                        "color": [
                          0.0,
                          0.0,
                          0.0,
                          1.0
                        ]
                      },
                      "text": null,
                      "image": null,
                      "children": [
                        {
                          "x": 385.0,
                          "y": 535.0,
                          "width": 40.0,
                          "height": 23.0,
                          "background_color": null,
                          "border": null,
                          "text": {
                            "lines": [
                              {
                                "text": "Price",
                                "x_offset": 0.0,
                                "y_offset": 0.0
                              }
                            ],
                            "font_family": "Helvetica",
                            "font_size": 16.0,
                            "bold": false,
                            "italic": false,
                            "color": [
                              0.0,
                              0.0,
                              0.0,
                              1.0
                            ],
                            "line_height": 22.4,
                            "text_align": "left",
                            "underline": false,
                            "list_marker": null
                          },
                          "image": null,
                          "children": []
                        }
                      ]
                    }
                  ]
                },
                {
                  "x": 64.0,
                  "y": 566.0,
                  "width": 467.0,
                  "height": 40.0,
                  "background_color": null,
                  "border": null,
                  "text": null,
                  "image": null,
                  "children": [
                    {
                      "x": 64.0,
                      "y": 566.0,
                      "width": 156.0,
                      "height": 40.0,
                      "background_color": null,
                      "border": {
                        "width": 1.0,
                        "color": [
                          0.0,
                          0.0,
                          0.0,
                          1.0
                        ]
                      },
                      "text": null,
                      "image": null,
                      "children": [
                        {
                          "x": 73.0,
                          "y": 575.0,
                          "width": 62.0,
                          "height": 22.0,
                          "background_color": null,
                          "border": null,
                          "text": {
                            "lines": [
                              {
                                "text": "Starter",
                                "x_offset": 0.0,
                                "y_offset": 0.0
                              }
                            ],
                            "font_family": "Helvetica",
                            "font_size": 16.0,
                            "bold": true,
                            "italic": false,
                            "color": [
                              0.0,
                              0.0,
                              0.0,
                              1.0
                            ],
                            "line_height": 22.4,
                            "text_align": "left",
                            "underline": false,
                            "list_marker": null
                          },
                          "image": null,
                          "children": []
                        }
                      ]
                    },
                    {
                      "x": 220.0,
                      "y": 566.0,
                      "width": 156.0,
                      "height": 40.0,
                      "background_color": null,
                      "border": {
                        "width": 1.0,
                        "color": [
                          0.0,
                          0.0,
                          0.0,
                          1.0
                        ]
                      },
                      "text": null,
                      "image": null,
                      "children": [
                        {
                          "x": 229.0,
                          "y": 575.0,
                          "width": 64.0,
                          "height": 22.0,
                          "background_color": null,
                          "border": null,
                          "text": {
                            "lines": [
                              {
                                "text": "Up to 10",
                                "x_offset": 0.0,
                                "y_offset": 0.0
                              }
                            ],
                            "font_family": "Helvetica",
                            "font_size": 16.0,
                            "bold": false,
                            "italic": false,
                            "color": [
                              0.0,
                              0.0,
                              0.0,
                              1.0
                            ],
                            "line_height": 22.4,
                            "text_align": "left",
                            "underline": false,
                            "list_marker": null
                          },
                          "image": null,
                          "children": []
                        }
                      ]
                    },
                    {
                      "x": 376.0,
                      "y": 566.0,
                      "width": 155.0,
                      "height": 40.0,
                      "background_color": null,
                      "border": {
                        "width": 1.0,
                        "color": [
                          0.0,
                          0.0,
                          0.0,
                          1.0
                        ]
                      },
                      "text": null,
                      "image": null,
                      "children": [
                        {
                          "x": 385.0,
                          "y": 575.0,
                          "width": 48.0,
                          "height": 22.0,
                          "background_color": null,
                          "border": null,
                          "text": {
                            "lines": [
                              {
                                "text": "$29/mo",
                                "x_offset": 0.0,
                                "y_offset": 0.0
                              }
                            ],
                            "font_family": "Helvetica",
                            "font_size": 16.0,
                            "bold": false,
                            "italic": false,
                            "color": [
                              0.0,
                              0.0,
                              0.0,
                              1.0
                            ],
                            "line_height": 22.4,
                            "text_align": "left",
                            "underline": false,
                            "list_marker": null
                          },
                          "image": null,
                          "children": []
                        }
                      ]
                    }
                  ]
                },
                {
                  "x": 64.0,
                  "y": 607.0,
                  "width": 467.0,
                  "height": 41.0,
                  "background_color": null,
                  "border": null,
                  "text": null,
                  "image": null,
                  "children": [
                    {
                      "x": 64.0,
                      "y": 607.0,
                      "width": 156.0,
                      "height": 41.0,
                      "background_color": null,
                      "border": {
                        "width": 1.0,
                        "color": [
                          0.0,
                          0.0,
                          0.0,
                          1.0
                        ]
                      },
                      "text": null,
                      "image": null,
                      "children": [
                        {
                          "x": 73.0,
                          "y": 616.0,
                          "width": 26.0,
                          "height": 23.0,
                          "background_color": null,
                          "border": null,
                          "text": {
                            "lines": [
                              {
                                "text": "Pro",
                                "x_offset": 0.0,
                                "y_offset": 0.0
                              }
                            ],
                            "font_family": "Helvetica",
                            "font_size": 16.0,
                            "bold": true,
                            "italic": false,
                            "color": [
                              0.0,
                              0.0,
                              0.0,
                              1.0
                            ],
                            "line_height": 22.4,
                            "text_align": "left",
                            "underline": false,
                            "list_marker": null
                          },
                          "image": null,
                          "children": []
                        }
                      ]
                    },
                    {
                      "x": 220.0,
                      "y": 607.0,
                      "width": 156.0,
                      "height": 41.0,
                      "background_color": null,
                      "border": {
                        "width": 1.0,
                        "color": [
                          0.0,
                          0.0,
                          0.0,
                          1.0
                        ]
                      },
                      "text": null,
                      "image": null,
                      "children": [
                        {
                          "x": 229.0,
                          "y": 616.0,
                          "width": 72.0,
                          "height": 23.0,
                          "background_color": null,
                          "border": null,
                          "text": {
                            "lines": [
                              {
                                "text": "Up to 100",
                                "x_offset": 0.0,
                                "y_offset": 0.0
                              }
                            ],
                            "font_family": "Helvetica",
                            "font_size": 16.0,
                            "bold": false,
                            "italic": false,
                            "color": [
                              0.0,
                              0.0,
                              0.0,
                              1.0
                            ],
                            "line_height": 22.4,
                            "text_align": "left",
                            "underline": false,
                            "list_marker": null
                          },
                          "image": null,
                          "children": []
                        }
                      ]
                    },
                    {
                      "x": 376.0,
                      "y": 607.0,
                      "width": 155.0,
                      "height": 41.0,
                      "background_color": null,
                      "border": {
                        "width": 1.0,
                        "color": [
                          0.0,
                          0.0,
                          0.0,
                          1.0
                        ]
                      },
                      "text": null,
                      "image": null,
                      "children": [
                        {
                          "x": 385.0,
                          "y": 616.0,
                          "width": 48.0,
                          "height": 23.0,
                          "background_color": null,
                          "border": null,
                          "text": {
                            "lines": [
                              {
                                "text": "$99/mo",
                                "x_offset": 0.0,
                                "y_offset": 0.0
                              }
                            ],
                            "font_family": "Helvetica",
                            "font_size": 16.0,
                            "bold": false,
                            "italic": false,
                            "color": [
                              0.0,
                              0.0,
                              0.0,
                              1.0
                            ],
                            "line_height": 22.4,
                            "text_align": "left",
                            "underline": false,
                            "list_marker": null
                          },
                          "image": null,
                          "children": []
                        }
                      ]
                    }
                  ]
                },
                {
                  "x": 64.0,
                  "y": 647.0,
                  "width": 467.0,
                  "height": 40.0,
                  "background_color": null,
                  "border": null,
                  "text": null,
                  "image": null,
                  "children": [
                    {
                      "x": 64.0,
                      "y": 647.0,
                      "width": 156.0,
                      "height": 40.0,
                      "background_color": null,
                      "border": {
                        "width": 1.0,
                        "color": [
                          0.0,
                          0.0,
                          0.0,
                          1.0
                        ]
                      },
                      "text": null,
                      "image": null,
                      "children": [
                        {
                          "x": 73.0,
                          "y": 656.0,
                          "width": 88.0,
                          "height": 22.0,
                          "background_color": null,
                          "border": null,
                          "text": {
                            "lines": [
                              {
                                "text": "Enterprise",
                                "x_offset": 0.0,
                                "y_offset": 0.0
                              }
                            ],
                            "font_family": "Helvetica",
                            "font_size": 16.0,
                            "bold": true,
                            "italic": false,
                            "color": [
                              0.0,
                              0.0,
                              0.0,
                              1.0
                            ],
                            "line_height": 22.4,
                            "text_align": "left",
                            "underline": false,
                            "list_marker": null
                          },
                          "image": null,
                          "children": []
                        }
                      ]
                    },
                    {
                      "x": 220.0,
                      "y": 647.0,
                      "width": 156.0,
                      "height": 40.0,
                      "background_color": null,
                      "border": {
                        "width": 1.0,
                        "color": [
                          0.0,
                          0.0,
                          0.0,
                          1.0
                        ]
                      },
                      "text": null,
                      "image": null,
                      "children": [
                        {
                          "x": 229.0,
                          "y": 656.0,
                          "width": 72.0,
                          "height": 22.0,
                          "background_color": null,
                          "border": null,
                          "text": {
                            "lines": [
                              {
                                "text": "Unlimited",
                                "x_offset": 0.0,
                                "y_offset": 0.0
                              }
                            ],
                            "font_family": "Helvetica",
                            "font_size": 16.0,
                            "bold": false,
                            "italic": false,
                            "color": [
                              0.0,
                              0.0,
                              0.0,
                              1.0
                            ],
                            "line_height": 22.4,
                            "text_align": "left",
                            "underline": false,
                            "list_marker": null
                          },
                          "image": null,
                          "children": []
                        }
                      ]
                    },
                    {
                      "x": 376.0,
                      "y": 647.0,
                      "width": 155.0,
                      "height": 40.0,
                      "background_color": null,
                      "border": {
                        "width": 1.0,
                        "color": [
                          0.0,
                          0.0,
                          0.0,
                          1.0
                        ]
                      },
                      "text": null,
                      "image": null,
                      "children": [
                        {
                          "x": 385.0,
                          "y": 656.0,
                          "width": 80.0,
                          "height": 22.0,
                          "background_color": null,
                          "border": null,
                          "text": {
                            "lines": [
                              {
                                "text": "Contact us",
                                "x_offset": 0.0,
                                "y_offset": 0.0
                              }
                            ],
                            "font_family": "Helvetica",
                            "font_size": 16.0,
                            "bold": false,
                            "italic": false,
                            "color": [
                              0.0,
                              0.0,
                              0.0,
                              1.0
                            ],
                            "line_height": 22.4,
                            "text_align": "left",
                            "underline": false,
                            "list_marker": null
                          },
                          "image": null,
                          "children": []
                        }
                      ]
                    }
                  ]
                }
              ]
            }
          ]
        }
      ]
    }
  ]
}